ugbio_freec/__init__.py
ugbio_freec/generate_control_freec_config.py
ugbio_freec-1.20.0.dist-info/METADATA
ugbio_freec-1.20.0.dist-info/WHEEL
ugbio_freec-1.20.0.dist-info/entry_points.txt
ugbio_freec-1.20.0.dist-info/top_level.txt
ugbio_freec-1.20.0.dist-info/RECORD
