Metadata-Version: 2.4
Name: ugbio_freec
Version: 1.20.0
Summary: Ultima Genomics FREEC
Author-email: Tammy Biniashvili <tammy.biniashvili@ultimagen.com>, Avigail Moldovan <avigail.moldovan@ultimagen.com>
License: Apache-2.0
Requires-Python: >=3.11
Requires-Dist: pandas<3.0.0,>=2.2.2
Requires-Dist: pyfaidx<1.0.0,>=0.8.1
